Metadata-Version: 1.0
Name: py3gui
Version: 0.0.4
Summary: Easy gui builder for python.
Home-page: UNKNOWN
Author: UNKNOWN
Author-email: UNKNOWN
License: UNKNOWN
Platform: UNKNOWN
